{"v":3,"stories":{"button--primary":{"id":"button--primary","name":"Primary","title":"Button","importPath":"./src/components/button/button.stories.tsx","tags":["story"],"kind":"Button","story":"Primary","parameters":{"__id":"button--primary","docsOnly":false,"fileName":"./src/components/button/button.stories.tsx"}},"button--secondary":{"id":"button--secondary","name":"Secondary","title":"Button","importPath":"./src/components/button/button.stories.tsx","tags":["story"],"kind":"Button","story":"Secondary","parameters":{"__id":"button--secondary","docsOnly":false,"fileName":"./src/components/button/button.stories.tsx"}},"button--delete":{"id":"button--delete","name":"Delete","title":"Button","importPath":"./src/components/button/button.stories.tsx","tags":["story"],"kind":"Button","story":"Delete","parameters":{"__id":"button--delete","docsOnly":false,"fileName":"./src/components/button/button.stories.tsx"}},"chart--base":{"id":"chart--base","name":"Base","title":"Chart","importPath":"./src/components/chart/chart.stories.tsx","tags":["story"],"kind":"Chart","story":"Base","parameters":{"__id":"chart--base","docsOnly":false,"fileName":"./src/components/chart/chart.stories.tsx"}},"tablerow--bitcoin":{"id":"tablerow--bitcoin","name":"Bitcoin","title":"TableRow","importPath":"./src/components/table/tableRow/tableRow.stories.tsx","tags":["story"],"kind":"TableRow","story":"Bitcoin","parameters":{"__id":"tablerow--bitcoin","docsOnly":false,"fileName":"./src/components/table/tableRow/tableRow.stories.tsx"}}}}
